inlineegg/WindowsSyscall.py
inlineegg/__init__.py
inlineegg/exelib.py
inlineegg/inlineegg.py
inlineegg/inlineegg_test.py
inlineegg/inlineegg_win_test.py
InlineEgg_ng-1.8.dist-info/METADATA
InlineEgg_ng-1.8.dist-info/WHEEL
InlineEgg_ng-1.8.dist-info/top_level.txt
InlineEgg_ng-1.8.dist-info/RECORD
