Metadata-Version: 2.1
Name: InlineEgg-ng
Version: 1.8
Summary: Collection of classes for creating small assembly programs. These are specially tailored for eggs/shellcode creation.
Home-page: http://oss.coresecurity.com/projects/inlineegg.html
Author: Gerardo Richarte
Author-email: gera@coresecurity.com
License: UNKNOWN
Platform: UNKNOWN
